{
   "application": {
      "flow": {
         "flow.json": "{\"places\":{\"entry\":{\"redirectTo\":\"tools/page\"},\"tools/:tab\":{\"page\":\"tools\"}}}"
      },
      "layouts": {
         "tools": {
            "default.theme": {
               "css": {
                  "tools.css": 1
               },
               "tools.html": "<div class=\"fluid-container\"> <div class=\"app-toolbar\"> <div class=\"col col-lg-12 first last\" data-ax-widget-area=\"toolbar\"></div> </div> </div> "
            }
         }
      },
      "pages": {
         "tools.json": "{\"layout\":\"tools\",\"areas\":{\"activities\":[{\"widget\":\"developer-tools/ax-host-connector-widget\",\"features\":{\"events\":{\"stream\":\"eventBusItems\"},\"log\":{\"stream\":\"logItems\"},\"pageInfo\":{\"resource\":\"pageInfo\"},\"grid\":{\"resource\":\"gridSettings\"}}}],\"toolbar\":[{\"widget\":\"developer-tools/ax-developer-toolbar-widget\",\"id\":\"toolbar\",\"features\":{\"grid\":{\"resource\":\"gridSettings\"},\"tabs\":{\"parameter\":\"tab\"}}}],\"toolbar.page\":[{\"widget\":\"developer-tools/ax-page-inspector-widget\",\"features\":{\"pageInfo\":{\"resource\":\"pageInfo\"},\"filter\":{\"resource\":\"eventFilter\"}}}],\"toolbar.events\":[{\"widget\":\"developer-tools/ax-events-display-widget\",\"features\":{\"events\":{\"stream\":\"eventBusItems\"},\"filter\":{\"resource\":\"eventFilter\"}}}],\"toolbar.logs\":[{\"widget\":\"developer-tools/ax-log-display-widget\",\"features\":{\"log\":{\"stream\":\"logItems\"}}}]}}"
      }
   },
   "bower_components": {
      "laxar-affix-control": {
         "control.json": "{\"name\":\"ax-affix-control\",\"integration\":{\"technology\":\"angular\"}}"
      },
      "laxar-input-control": {
         "control.json": "{\"name\":\"ax-input-control\",\"integration\":{\"technology\":\"angular\"}}"
      },
      "laxar-uikit": {
         "dist": {
            "themes": {
               "default.theme": {
                  "css": {
                     "theme.css": 1
                  }
               }
            }
         }
      }
   },
   "includes": {
      "widgets": {
         "developer-tools": {
            "ax-developer-toolbar-widget": {
               "default.theme": {
                  "ax-developer-toolbar-widget.html": "<div class=\"row text-right\"> <button class=\"btn btn-link\" type=\"button\" data-ng-if=\"resources.grid\" data-ng-click=\"toggleGrid()\" ><i class=\"fa\" data-ng-class=\"{ 'fa-toggle-off': !model.gridOverlay, 'fa-toggle-on': model.gridOverlay }\" ></i>&nbsp;{{model.gridOverlay ? 'Turn off grid overlay' : 'Turn on grid overlay'}}</button> <button class=\"btn btn-link\" type=\"button\" data-ng-click=\"toggleWidgetOutline()\" ><i class=\"fa\" data-ng-class=\"{ 'fa-toggle-off': !model.widgetOverlay, 'fa-toggle-on': model.widgetOverlay }\" ></i>&nbsp;{{model.widgetOverlay ? 'Turn off widget outline' : 'Turn on widget outline'}}</button> </div> <ul class=\"nav nav-tabs\" role=\"tablist\"> <li data-ng-class=\"{ 'ax-active': model.activeTab=='page' }\" ><a href=\"javascript:void(0);\" data-ng-click=\"activateTab('page')\">Page</a></li> <li data-ng-class=\"{ 'ax-active': model.activeTab=='events' }\" ><a href=\"javascript:void(0);\" data-ng-click=\"activateTab('events')\">Events</a></li> <li data-ng-class=\"{ 'ax-active': model.activeTab=='logs' }\" ><a href=\"javascript:void(0);\" data-ng-click=\"activateTab('logs')\">Logs</a></li> </ul> <div class=\"app-tab app-tab-page\" data-ax-widget-area=\"page\" data-ng-show=\"model.activeTab=='page'\"></div> <div class=\"app-tab app-tab-content\" data-ax-widget-area=\"events\" data-ng-show=\"model.activeTab=='events'\"></div> <div class=\"app-tab app-tab-content\" data-ax-widget-area=\"logs\" data-ng-show=\"model.activeTab=='logs'\"></div> ",
                  "css": {
                     "ax-developer-toolbar-widget.css": 1
                  }
               },
               "widget.json": "{\"name\":\"AxDeveloperToolbarWidget\",\"description\":\"Allows to show widget outlines and to display an alignment grid for the host application\",\"integration\":{\"technology\":\"angular\",\"type\":\"widget\"},\"features\":{\"$schema\":\"http://json-schema.org/draft-04/schema#\",\"type\":\"object\",\"required\":[\"grid\"],\"properties\":{\"grid\":{\"type\":\"object\",\"required\":[\"resource\"],\"properties\":{\"resource\":{\"type\":\"string\",\"format\":\"topic\",\"axRole\":\"inlet\"}}},\"tabs\":{\"type\":\"object\",\"required\":[\"parameter\"],\"properties\":{\"parameter\":{\"type\":\"string\",\"format\":\"topic\"}}}}}}"
            },
            "ax-events-display-widget": {
               "default.theme": {
                  "ax-events-display-widget.html": "<div class=\"ax-affix-area\" data-ax-affix data-ax-affix-offset-top=\"100\"> <div class=\"ax-button-wrapper form-inline\"> <div class=\"form-group form-group-sm\"> <label data-ax-for=\"'search'\"><small>Filters:</small></label> <input class=\"form-control input-sm\" placeholder=\"Search (RegExp)\" data-ax-id=\"'search'\" data-ng-model=\"model.settings.namePattern\"> <label data-ax-for=\"'limit'\"><small>Limit:</small></label> <input class=\"form-control input-sm\" data-ax-input=\"integer\" data-ng-model-options=\"{ updateOn: 'default' }\" data-ax-input-minimum-value=\"0\" data-ax-input-maximum-value=\"features.events.bufferSize\" placeholder=\"0-{{ features.events.bufferSize }}\" maxlength=\"4\" data-ax-id=\"'limit'\" data-ng-model=\"model.settings.visibleEventsLimit\"> </div> <!-- Filters menu --> <div class=\"btn-group btn-group-sm\" data-ng-class=\"{ 'open': view.showPatterns }\" data-ng-mouseenter=\"view.showPatterns = true\" data-ng-mouseleave=\"view.showPatterns = false\"> <button type=\"button\" class=\"btn btn-default dropdown-toggle\" data-toggle=\"dropdown\" aria-expanded=\"{{ view.showPatterns }}\"> More <span class=\"caret\"></span> </button> <div class=\"dropdown-menu container col-lg-6\" role=\"menu\"> <div class=\"row\"> <div class=\"ax-event-settings-col first\"> <h4>Patterns</h4> <div data-ng-repeat=\"pattern in model.patterns track by pattern.name\"> <button type=\"button\" class=\"btn btn-link ax-event-setting-toggle\" data-ng-click=\"model.settings.patterns[ pattern.name ] = !model.settings.patterns[ pattern.name ]\"> <span class=\"ax-event-pattern\" data-ng-bind-html=\"pattern.htmlIcon\"></span> {{ pattern.name }} <i class=\"fa pull-right ax-event-setting-toggle\" data-ng-class=\"{ 'fa-toggle-off': !model.settings.patterns[ pattern.name ], 'fa-toggle-on': model.settings.patterns[ pattern.name ] }\"></i> </button> </div> </div> <div class=\"ax-event-settings-col last\"> <h4>Interactions</h4> <div data-ng-repeat=\"(interaction, enabled) in model.settings.interactions track by interaction\"> <button type=\"button\" class=\"btn btn-link ax-event-setting-toggle\" data-ng-click=\"model.settings.interactions[ interaction ] = !enabled\" >{{ interaction }}<i class=\"fa pull-right ax-event-setting-toggle\" data-ng-class=\"{ 'fa-toggle-off': !enabled, 'fa-toggle-on': enabled }\"></i> </button> </div> <h4>Sources</h4> <div data-ng-repeat=\"(source, enabled) in model.settings.sources track by source\"> <button type=\"button\" class=\"btn btn-link ax-event-setting-toggle\" data-ng-click=\"model.settings.sources[ source ] = !enabled\" >{{ source }}<i class=\"fa pull-right ax-event-setting-toggle\" data-ng-class=\"{ 'fa-toggle-off': !enabled, 'fa-toggle-on': enabled }\"></i> </button> </div> </div> </div> <div class=\"row\"> <div class=\"ax-event-settings-col first\">&nbsp;</div> <div class=\"ax-event-settings-col last\"> <div class=\"pull-right\"> <button type=\"button\" class=\"btn btn-xs btn-primary\" data-ng-click=\"commands.setAll( true )\">All On</button> <button type=\"button\" class=\"btn btn-xs btn-primary\" data-ng-click=\"commands.setAll( false )\">All Off</button> <button type=\"button\" class=\"btn btn-xs\" data-ng-click=\"commands.setDefaults()\">Defaults</button> </div> </div> </div> </div> </div> <button class=\"btn btn-primary btn-sm\" type=\"button\" data-ng-class=\"{ 'ax-disabled': !model.eventInfos.length }\" data-ng-click=\"commands.discard()\">Discard Events</button> </div> <div class=\"form-inline ax-events-filter-items\" data-ng-if=\"resources.filter.topics.length || resources.filter.participants.length\"> <a class=\"btn btn-xs btn-link\" href=\"#/tools/page\">Page selection</a> <span class=\"btn btn-xs btn-info\" data-ng-repeat=\"item in resources.filter.topics track by item.topic\" data-ng-class=\"'ax-events-display-pattern-' + item.pattern\"> {{item.topic}} </span><span class=\"btn btn-xs btn-info\" data-ng-repeat=\"item in resources.filter.participants track by item.participant\" data-ng-class=\"'ax-events-display-kind-' + item.kind\"> {{item.participant}} </span> </div> </div> <div data-ng-if=\"!model.eventInfos.length\" class=\"text-large\"> <h4 class=\"text-primary\">Empty Events List</h4> <p><i class=\"fa fa-clock-o\"></i> Waiting for events from host application...</p> </div> <div data-ng-if=\"model.eventInfos.length && !model.visibleEventInfos.length\" class=\"text-large\"> <h4 class=\"text-primary\">0/{{ model.eventInfos.length }} Event Items</h4> <p>No events matching current filters.</p> <p><button type=\"button\" class=\"btn btn-sm btn-primary\" data-ng-click=\"commands.clearFilters()\">Show All</button></p> </div> <div data-ng-if=\"model.visibleEventInfos.length\" class=\"text-large\"> <h4 class=\"text-primary\">{{ model.visibleEventInfos.length }}/{{ model.eventInfos.length }} Events</h4> </div> <table data-ng-if=\"model.visibleEventInfos.length\" class=\"table\"> <colgroup> <col class=\"ax-col-pattern-icon\"> <col class=\"ax-col-interaction\"> <col class=\"ax-col-payload-icon\"> <col class=\"ax-col-name\"> <col class=\"ax-col-cycle\"> <col class=\"ax-col-source\"> <col class=\"ax-col-target\"> <col class=\"ax-col-timestamp\"> </colgroup> <thead> <tr> <th>&nbsp;</th> <th>Action</th> <th>&nbsp;</th> <th>Event Name</th> <th class=\"text-right\">Cycle</th> <th>Source</th> <th>Target</th> <th class=\"text-right\">Timestamp</th> </tr> </thead> <tbody data-ng-repeat=\"event in model.visibleEventInfos\" data-ng-class=\"'ax-event-interaction-' + event.interaction + ( event.selected ? ' ax-event-selected' : '' )\" data-ng-click=\"commands.select( event )\"> <tr class=\"ax-event-summary\"> <td class=\"ax-col-pattern-icon\" title=\"{{ event.pattern }}\" data-ng-bind-html=\"view.patternsByName[ event.pattern ].htmlIcon\"></td> <td class=\"ax-col-interaction\"><em>{{event.interaction}}</em></td> <td> <button type=\"button\" class=\"btn-link btn-info\" data-ng-if=\"event.interaction == 'publish' && !event.showDetails\" data-ng-click=\"event.showDetails = true; $event.stopPropagation();\"><i class=\"fa fa-plus-square\">&nbsp;</i></button> <button type=\"button\" class=\"btn-link btn-info\" data-ng-if=\"event.interaction == 'publish' && event.showDetails\" data-ng-click=\"event.showDetails = false; $event.stopPropagation();\"><i class=\"fa fa-minus-square\" >&nbsp;</i></button> </td> <td data-ng-bind-html=\"event.htmlName\"></td> <td class=\"ax-col-cycle text-right\">{{event.cycleId}}</td> <td data-ng-bind-html=\"event.htmlSource\"></td> <td data-ng-bind-html=\"event.htmlTarget\"></td> <td class=\"text-right\">{{event.formattedTime}}</td> </tr> <tr class=\"ax-event-payload\" data-ng-if=\"event.showDetails\"> <td colspan=\"3\"></td> <td colspan=\"5\" ><pre>{{event.formattedEvent}}</pre></td> </tr> </tbody> </table> ",
                  "css": {
                     "ax-events-display-widget.css": 1
                  }
               },
               "widget.json": "{\"name\":\"AxEventsDisplayWidget\",\"description\":\"Displays events from the event bus.\",\"integration\":{\"technology\":\"angular\",\"type\":\"widget\"},\"controls\":[\"laxar-input-control\",\"laxar-affix-control\"],\"features\":{\"$schema\":\"http://json-schema.org/draft-04/schema#\",\"type\":\"object\",\"requires\":[\"events\"],\"properties\":{\"events\":{\"type\":\"object\",\"description\":\"Display event bus activity received through wrapper events.\",\"requires\":[\"stream\"],\"properties\":{\"stream\":{\"type\":\"string\",\"description\":\"The event topic through which to gather events.\"},\"bufferSize\":{\"type\":\"integer\",\"description\":\"Maximum number of event items to keep in memory.\",\"default\":5000}}},\"filter\":{\"type\":\"object\",\"description\":\"Controls filter settings\",\"properties\":{\"hidePatterns\":{\"type\":\"array\",\"description\":\"Controls pattern-related default filter settings\",\"default\":[\"visibility\",\"i18n\"]},\"hideSources\":{\"type\":\"array\",\"description\":\"Controls source-related default filter settings\",\"default\":[\"runtime\"]},\"hideInteractions\":{\"type\":\"array\",\"description\":\"Controls interaction-related default filter settings\",\"default\":[\"subscribe\",\"unsubscribe\"]},\"resource\":{\"type\":\"string\",\"description\":\"The event topic through which to receive filter information\",\"format\":\"topic\",\"axRole\":\"outlet\"}}},\"showLocalEvents\":{\"type\":\"object\",\"description\":\"Display page-local events.\",\"properties\":{\"enabled\":{\"type\":\"boolean\",\"description\":\"If true, any event from the same page is displayed.\",\"default\":false}}}}}}"
            },
            "ax-host-connector-widget": {
               "widget.json": "{\"name\":\"AxHostConnectorWidget\",\"description\":\"Connects the contents of the development window to the AxDeveloperToolsWidget\",\"integration\":{\"technology\":\"angular\",\"type\":\"widget\"},\"features\":{\"$schema\":\"http://json-schema.org/draft-04/schema#\",\"type\":\"object\",\"properties\":{\"events\":{\"type\":\"object\",\"description\":\"Publish a stream of event bus activity through wrapper events.\",\"properties\":{\"stream\":{\"type\":\"string\",\"description\":\"The topic through which to publish event items.\",\"default\":null}}},\"log\":{\"type\":\"object\",\"description\":\"Publish a stream of log items through wrapper events.\",\"properties\":{\"stream\":{\"type\":\"string\",\"description\":\"The topic through which to publish log items.\",\"default\":null}}},\"pageInfo\":{\"type\":\"object\",\"description\":\"Publish the current page for inspection.\",\"properties\":{\"resource\":{\"type\":\"string\",\"description\":\"The topic through which to publish the current page.\",\"default\":null}}},\"grid\":{\"type\":\"object\",\"description\":\"Publish application-specific grid configuration set by the host application.\",\"properties\":{\"resource\":{\"type\":\"string\",\"description\":\"A resource through which to publish grid settings.\",\"default\":null}}},\"development\":{\"type\":\"object\",\"properties\":{\"liveReload\":{\"type\":\"boolean\",\"default\":true}}}}}}"
            },
            "ax-log-display-widget": {
               "default.theme": {
                  "ax-log-display-widget.html": "<div class=\"ax-affix-area\" data-ax-affix data-ax-affix-offset-top=\"100\"> <div class=\"ax-button-wrapper\"> <button class=\"btn btn-primary btn-sm\" type=\"button\" data-ng-class=\"{ 'ax-disabled': !model.messages.length }\" data-ng-click=\"commands.discard()\">Clear</button> </div> </div> <div data-ng-if=\"!model.messages.length\" class=\"text-large\"> <h4 class=\"text-primary\">No Log Messages</h4> <p><i class=\"fa fa-clock-o\"></i> Waiting for messages from host application...</p> </div> <table data-ng-if=\"model.messages.length\" class=\"table table-striped table-hover\"> <thead> <tr> <th>Level</th> <th>Nachricht</th> <th>Ort</th> <th>Zeit</th> </tr> </thead> <tbody> <tr data-ng-repeat=\"message in model.messages\"> <td>{{message.level}}</td> <td>{{message.text}}</td> <td>{{message.location}}</td> <td>{{message.time | axLogDisplayFormattedDate}}</td> </tr> </tbody> </table> ",
                  "css": {
                     "ax-log-display-widget.css": 1
                  }
               },
               "widget.json": "{\"name\":\"AxLogDisplayWidget\",\"description\":\"Displays log messages to the user.\",\"integration\":{\"technology\":\"angular\",\"type\":\"widget\"},\"controls\":[\"laxar-affix-control\"],\"features\":{\"$schema\":\"http://json-schema.org/draft-04/schema#\",\"type\":\"object\",\"requires\":[\"log\"],\"log\":{\"type\":\"object\",\"description\":\"Display log messages received through wrapper events.\",\"properties\":{\"stream\":{\"type\":\"string\",\"description\":\"The topic through which to gather log messages.\"},\"bufferSize\":{\"type\":\"integer\",\"description\":\"Maximum number of log message items to keep in memory.\",\"default\":5000}}}}}"
            },
            "ax-page-inspector-widget": {
               "default.theme": {
                  "css": {
                     "ax-page-inspector-widget.css": 1
                  }
               },
               "widget.json": "{\"name\":\"ax-page-inspector-widget\",\"description\":\"Visualizes the widgets on the current page and their event connections\",\"integration\":{\"technology\":\"react\",\"type\":\"widget\"},\"features\":{\"$schema\":\"http://json-schema.org/draft-04/schema#\",\"type\":\"object\",\"properties\":{\"pageInfo\":{\"type\":\"object\",\"description\":\"Inspect page models received through wrapper events.\",\"requires\":[\"resource\"],\"properties\":{\"resource\":{\"type\":\"string\",\"description\":\"The event topic through which to monitor pages.\",\"format\":\"topic\",\"axRole\":\"inlet\"}}},\"filter\":{\"type\":\"object\",\"description\":\"Allows to filter by topic or widget/activity instance\",\"requires\":[\"resource\"],\"properties\":{\"resource\":{\"type\":\"string\",\"description\":\"The event topic through which to publish filter information\",\"format\":\"topic\",\"axRole\":\"outlet\"}}}}}}"
            }
         }
      }
   }
}
